deepevolution/__init__.py
deepevolution/deepevolution.py
deepevolution-0.0.4.dist-info/AUTHORS
deepevolution-0.0.4.dist-info/METADATA
deepevolution-0.0.4.dist-info/WHEEL
deepevolution-0.0.4.dist-info/top_level.txt
deepevolution-0.0.4.dist-info/RECORD
