Metadata-Version: 2.1
Name: deepevolution
Version: 0.0.4
Summary: A genetic algorithm to evolve tensorflow keras neural networks.
Home-page: http://github.com/ipazc/deepevolution
Author: Iván de Paz Centeno
Author-email: ipazc@unileon.es
License: UNKNOWN
Keywords: deepevolution genetic algorithm keras tensorflow evolve network
Platform: UNKNOWN
Classifier: Environment :: Console
Classifier: Intended Audience :: Developers
Classifier: Intended Audience :: Education
Classifier: Intended Audience :: Science/Research
Classifier: Natural Language :: English
Classifier: Programming Language :: Python :: 3.4
Classifier: Programming Language :: Python :: 3.5
Classifier: Programming Language :: Python :: 3.6
Classifier: Programming Language :: Python :: 3.7
Requires-Dist: numpy
Requires-Dist: pandas (>=1.1.0)
Requires-Dist: tqdm
Provides-Extra: tf
Requires-Dist: tensorflow (>=2.0.0) ; extra == 'tf'
Provides-Extra: tf_gpu
Requires-Dist: tensorflow-gpu (>=2.0.0) ; extra == 'tf_gpu'
